vinclude.py
vinclude-1.1.0.dist-info/licenses/LICENSE.txt
vinclude-1.1.0.dist-info/METADATA
vinclude-1.1.0.dist-info/WHEEL
vinclude-1.1.0.dist-info/entry_points.txt
vinclude-1.1.0.dist-info/top_level.txt
vinclude-1.1.0.dist-info/RECORD
