Metadata-Version: 2.4
Name: vinclude
Version: 1.1.0
Summary: Visual C/C++ project include graphs, in a simple command line UI, for Linux.
Author-email: 2xB <2xb.coding@uni-muenster.de>
Maintainer-email: 2xB <2xb.coding@uni-muenster.de>
License:                     GNU GENERAL PUBLIC LICENSE
Project-URL: Homepage, https://github.com/2xB/vinclude
Project-URL: Bug Reports, https://github.com/2xB/vinclude/issues
Project-URL: Source, https://github.com/2xB/vinclude/
Keywords: include,c,cpp,interactive,ncurses,visual
Classifier: Development Status :: 5 - Production/Stable
Classifier: Intended Audience :: Developers
Classifier: Topic :: Software Development
Classifier: License :: OSI Approved :: GNU General Public License v3 (GPLv3)
Classifier: Programming Language :: Python :: 3
Classifier: Programming Language :: Python :: 3.9
Classifier: Programming Language :: Python :: 3.10
Classifier: Programming Language :: Python :: 3.11
Classifier: Programming Language :: Python :: 3.12
Classifier: Programming Language :: Python :: 3.13
Classifier: Programming Language :: Python :: 3 :: Only
Classifier: Operating System :: POSIX :: Linux
Requires-Python: >=3.9
License-File: LICENSE.txt
Dynamic: license-file
